cupbearer/__init__.py
cupbearer/data/__init__.py
cupbearer/data/_shared.py
cupbearer/data/adversarial.py
cupbearer/data/backdoor_data.py
cupbearer/data/backdoors.py
cupbearer/data/pytorch.py
cupbearer/detectors/__init__.py
cupbearer/detectors/anomaly_detector.py
cupbearer/detectors/config.py
cupbearer/detectors/abstraction/__init__.py
cupbearer/detectors/abstraction/abstraction.py
cupbearer/detectors/abstraction/abstraction_detector.py
cupbearer/detectors/abstraction/adversarial_detector.py
cupbearer/detectors/mahalanobis/__init__.py
cupbearer/detectors/mahalanobis/helpers.py
cupbearer/detectors/mahalanobis/mahalanobis_detector.py
cupbearer/models/__init__.py
cupbearer/models/computations.py
cupbearer/scripts/eval_detector.py
cupbearer/scripts/make_adversarial_examples.py
cupbearer/scripts/train_classifier.py
cupbearer/scripts/train_detector.py
cupbearer/scripts/conf/eval_detector_conf.py
cupbearer/scripts/conf/make_adversarial_examples_conf.py
cupbearer/scripts/conf/train_classifier_conf.py
cupbearer/scripts/conf/train_detector_conf.py
cupbearer/tasks/__init__.py
cupbearer/tasks/_config.py
cupbearer/tasks/adversarial_examples.py
cupbearer/tasks/backdoor_detection.py
cupbearer/utils/config_groups.py
cupbearer/utils/custom_transforms.py
cupbearer/utils/logger.py
cupbearer/utils/optimizers.py
cupbearer/utils/scripts.py
cupbearer/utils/trainer.py
cupbearer/utils/utils.py
cupbearer-0.0.1.dist-info/LICENSE
cupbearer-0.0.1.dist-info/METADATA
cupbearer-0.0.1.dist-info/WHEEL
cupbearer-0.0.1.dist-info/top_level.txt
cupbearer-0.0.1.dist-info/RECORD
