Metadata-Version: 2.1
Name: cupbearer
Version: 0.0.1
Summary: A library for mechanistic anomaly detection
Author-email: Erik Jenner <erik@ejenner.com>
Project-URL: Homepage, https://github.com/ejnnr/cupbearer
Project-URL: Bug Tracker, https://github.com/ejnnr/cupbearer/issues
Classifier: Programming Language :: Python :: 3
Classifier: License :: OSI Approved :: MIT License
Classifier: Operating System :: OS Independent
Requires-Python: >=3.10
License-File: LICENSE
Requires-Dist: flax ~=0.7.0
Requires-Dist: jax ~=0.4.13
Requires-Dist: optax ~=0.1.7
Requires-Dist: orbax-checkpoint ~=0.2.7
Requires-Dist: numpy ~=1.24.2
Requires-Dist: scikit-learn ~=1.2.2
Requires-Dist: Pillow ~=9.4.0
Requires-Dist: torch ~=2.0.0
Requires-Dist: torchvision ~=0.15.1
Requires-Dist: simple-parsing ~=0.1.3
Requires-Dist: tqdm
Requires-Dist: loguru
Requires-Dist: matplotlib
Provides-Extra: dev
Requires-Dist: pytest ; extra == 'dev'
Requires-Dist: pre-commit ; extra == 'dev'
Provides-Extra: plots
Requires-Dist: iceberg-dsl ==0.0.6 ; extra == 'plots'
Provides-Extra: wandb
Requires-Dist: wandb ; extra == 'wandb'
